velocix/__init__.py
velocix/__main__.py
velocix/cli.py
velocix/config/__init__.py
velocix/config/settings.py
velocix/core/__init__.py
velocix/core/app.py
velocix/core/depends.py
velocix/core/exceptions.py
velocix/core/middleware.py
velocix/core/request.py
velocix/core/response.py
velocix/core/router.py
velocix/http/__init__.py
velocix/http/client.py
velocix/http/multipart.py
velocix/middleware/__init__.py
velocix/middleware/compression.py
velocix/middleware/request_id.py
velocix/middleware/security.py
velocix/monitoring/__init__.py
velocix/monitoring/health.py
velocix/monitoring/metrics.py
velocix/openapi/__init__.py
velocix/openapi/auto_docs.py
velocix/openapi/decorators.py
velocix/openapi/decorators_style.py
velocix/openapi/generator.py
velocix/openapi/models.py
velocix/security/__init__.py
velocix/security/cors.py
velocix/security/jwt.py
velocix/security/password.py
velocix/security/ratelimit.py
velocix/testing/__init__.py
velocix/testing/client.py
velocix/validation/__init__.py
velocix/validation/models.py
velocix/validation/validators.py
velocix/websocket/__init__.py
velocix/websocket/connection.py
velocix-0.1.3.dist-info/METADATA
velocix-0.1.3.dist-info/WHEEL
velocix-0.1.3.dist-info/top_level.txt
velocix-0.1.3.dist-info/RECORD
