Metadata-Version: 2.4
Name: velocix
Version: 0.1.3
Summary: A learning project - ASGI web framework built to understand async Python patterns
Home-page: https://github.com/magi8101/velocix
Author: Magi Sharma
Author-email: Magi Sharma <sharmamagio0@gmail.com>
License: MIT
Project-URL: Homepage, https://github.com/magi8101/velocix
Project-URL: Repository, https://github.com/magi8101/velocix
Project-URL: Issues, https://github.com/magi8101/velocix/issues
Classifier: Development Status :: 3 - Alpha
Classifier: Intended Audience :: Developers
Classifier: Programming Language :: Python :: 3
Classifier: Programming Language :: Python :: 3.11
Classifier: Programming Language :: Python :: 3.12
Classifier: Framework :: AsyncIO
Requires-Python: >=3.11
Requires-Dist: granian>=1.0.0
Requires-Dist: orjson>=3.9.0
Requires-Dist: pydantic<3.0.0,>=2.0.0
Requires-Dist: pydantic-settings>=2.0.0
Requires-Dist: asyncpg>=0.29.0
Requires-Dist: prometheus-client>=0.19.0
Requires-Dist: python-jose[cryptography]>=3.3.0
Requires-Dist: python-multipart>=0.0.6
Requires-Dist: httpx>=0.25.0
Requires-Dist: aiofiles>=23.0.0
Provides-Extra: dev
Requires-Dist: pytest>=7.4.0; extra == "dev"
Requires-Dist: pytest-asyncio>=0.21.0; extra == "dev"
Requires-Dist: mypy>=1.7.0; extra == "dev"
Requires-Dist: black>=23.0.0; extra == "dev"
Requires-Dist: isort>=5.12.0; extra == "dev"
Dynamic: author
Dynamic: home-page
Dynamic: requires-python
